py_behrtech/__init__.py
py_behrtech/calls.py
py_behrtech/exceptions.py
py_behrtech/functions.py
py_behrtech/setup.py
py_behrtech/Calls/__init__.py
py_behrtech/Calls/azure.py
py_behrtech/Calls/baseStation.py
py_behrtech/Calls/messages.py
py_behrtech/Calls/models.py
py_behrtech/Calls/mqtt.py
py_behrtech/Calls/nodes.py
py_behrtech/Calls/plugins.py
py_behrtech/Calls/system.py
py_behrtech/Calls/user.py
py_behrtech/Parsers/__init__.py
py_behrtech/Parsers/defaults.py
py_behrtech/Parsers/json_parsers.py
py_behrtech/Parsers/messageParser.py
py_behrtech/Parsers/modelParser.py
py_behrtech/Parsers/nodeParser.py
py_behrtech-2021.7.21.2.dist-info/METADATA
py_behrtech-2021.7.21.2.dist-info/WHEEL
py_behrtech-2021.7.21.2.dist-info/top_level.txt
py_behrtech-2021.7.21.2.dist-info/RECORD
