Metadata-Version: 2.1
Name: py-behrtech
Version: 2021.7.21.2
Summary: A package to interface with BehrTech's gateway API for requesting and parsing data
Home-page: https://github.com/Vern-Technologies/py_behrtech
Author: Matthew Ashley
Author-email: matthewashley@verntechnologies.com
License: MIT
Platform: UNKNOWN
Classifier: Programming Language :: Python :: 3
Classifier: License :: OSI Approved :: MIT License
Classifier: Operating System :: OS Independent
Requires-Python: >=3.9
Requires-Dist: requests
